cmsis_svd_codec/__init__.py
cmsis_svd_codec/encoder.py
cmsis_svd_codec-0.1.0.dist-info/LICENSE
cmsis_svd_codec-0.1.0.dist-info/METADATA
cmsis_svd_codec-0.1.0.dist-info/WHEEL
cmsis_svd_codec-0.1.0.dist-info/top_level.txt
cmsis_svd_codec-0.1.0.dist-info/RECORD
