Metadata-Version: 2.1
Name: cmsis-svd-codec
Version: 0.1.0
Summary: A CMSIS-SVD file encoder to generate svd files programmatically, which is useful when parsing other descriptor formats.
Home-page: https://github.com/engdoreis/cmsis-svd-codec
Author: Douglas Reis
Author-email: engdoreis@gmail.com
License: Apache 2.0
Platform: UNKNOWN
Classifier: License :: OSI Approved :: Apache Software License
Classifier: Programming Language :: Python :: 3.9
Classifier: Operating System :: OS Independent
Requires-Python: >=3.9
License-File: LICENSE
Requires-Dist: lxml (>=4.9.2)
